piest/__init__.py
piest/dict.py
piest/file.py
piest/list.py
piest/meta.py
piest-0.1.1.dist-info/LICENSE
piest-0.1.1.dist-info/METADATA
piest-0.1.1.dist-info/WHEEL
piest-0.1.1.dist-info/top_level.txt
piest-0.1.1.dist-info/RECORD
